emgdecomp/__init__.py
emgdecomp/_data.py
emgdecomp/_util.py
emgdecomp/decomposition.py
emgdecomp/parameters.py
emgdecomp/plots.py
emgdecomp/tests/__init__.py
emgdecomp/tests/_simulations.py
emgdecomp/tests/test_decomposition.py
emgdecomp-0.1.0.dist-info/LICENSE
emgdecomp-0.1.0.dist-info/METADATA
emgdecomp-0.1.0.dist-info/WHEEL
emgdecomp-0.1.0.dist-info/top_level.txt
emgdecomp-0.1.0.dist-info/RECORD
